reprograph/__init__.py
reprograph/reprograph.py
reprograph-0.1.0.dist-info/LICENSE
reprograph-0.1.0.dist-info/WHEEL
reprograph-0.1.0.dist-info/METADATA
reprograph-0.1.0.dist-info/RECORD
