Metadata-Version: 2.1
Name: reprograph
Version: 0.1.0
Summary: Framework for humane data analysis and reporting
Home-page: https://github.com/datagazing/reprograph
Author: Brendan Strejcek
Author-email: brendan@datagazing.com
Requires-Python: >=3.7
Classifier: License :: OSI Approved :: MIT License
